spotcli/__init__.py
spotcli/__main__.py
spotcli/auth.py
spotcli/console.py
spotcli/utils.py
spotcli/components/__init__.py
spotcli/components/header.py
spotcli/components/layout.py
spotcli-0.1.4.dist-info/LICENSE
spotcli-0.1.4.dist-info/METADATA
spotcli-0.1.4.dist-info/WHEEL
spotcli-0.1.4.dist-info/entry_points.txt
spotcli-0.1.4.dist-info/top_level.txt
spotcli-0.1.4.dist-info/RECORD
