Metadata-Version: 2.1
Name: spotcli
Version: 0.1.4
Summary: Cli tool to use spotify from terminal
Home-page: https://github.com/micheledinelli/spotcli
Author: Dinelli Michele
Author-email: dinellimichele00@gmail.com
License: MIT
Platform: any
Classifier: Intended Audience :: Developers
Classifier: Intended Audience :: Customer Service
Classifier: Operating System :: Microsoft
Classifier: Operating System :: MacOS :: MacOS X
Classifier: Operating System :: Unix
Classifier: Operating System :: POSIX
Classifier: Programming Language :: Python
Classifier: Topic :: Software Development
Classifier: Topic :: Software Development :: Libraries
Classifier: Topic :: Software Development :: Libraries :: Python Modules
Classifier: Topic :: System :: Software Distribution
Classifier: Topic :: Utilities
License-File: LICENSE
Requires-Dist: spotipy
Requires-Dist: rich
